bio_reasoning/__init__.py
bio_reasoning/coordinator.py
bio_reasoning/utils.py
bio_reasoning/layers/__init__.py
bio_reasoning/layers/c.py
bio_reasoning/layers/a/__init__.py
bio_reasoning/layers/a/parametric_memory.py
bio_reasoning/layers/b/__init__.py
bio_reasoning/layers/b/utils.py
bio_reasoning/layers/b/visual_describer.py
bio_reasoning/layers/c/__init__.py
bio_reasoning/layers/c/arxiv.py
bio_reasoning/layers/c/biorxiv.py
bio_reasoning/layers/c/pubmed.py
bio_reasoning/reasoning/__init__.py
bio_reasoning/reasoning/basics.py
bio_reasoning/reasoning/example_reasoning.py
bio_reasoning/reasoning/prompts.py
bio_reasoning-0.1.0.dist-info/METADATA
bio_reasoning-0.1.0.dist-info/WHEEL
bio_reasoning-0.1.0.dist-info/top_level.txt
bio_reasoning-0.1.0.dist-info/RECORD
