Metadata-Version: 2.4
Name: bio-reasoning
Version: 0.1.0
Summary: Biological Reasoning System
Author-email: Thomas Brettin <brettint@gmail.com>, Peng Ding <oaklight@gmx.com>
Classifier: Development Status :: 3 - Alpha
Classifier: Intended Audience :: Developers
Classifier: Programming Language :: Python :: 3
Classifier: Topic :: Software Development :: Libraries :: Python Modules
Classifier: Topic :: Scientific/Engineering :: Artificial Intelligence
Requires-Python: >=3.10
Requires-Dist: openai>=1.79.0
Requires-Dist: cicada-agent>=0.7.4
Requires-Dist: loguru>=0.7.3
Requires-Dist: httpx>=0.28.1
Requires-Dist: toolregistry>=0.4.12
Requires-Dist: python-dotenv>=1.1.0
Provides-Extra: dev
Requires-Dist: pyright>=1.1.402; extra == "dev"
Requires-Dist: ruff>=0.12; extra == "dev"
Requires-Dist: build>=1.2.2.post1; extra == "dev"
Requires-Dist: twine>=6.1.0; extra == "dev"
